featsql/__init__.py
featsql/_modidx.py
featsql/featmysql.py
featsql/featsnow.py
featsql/featsqlite.py
featsql-0.1.1.dist-info/LICENSE
featsql-0.1.1.dist-info/METADATA
featsql-0.1.1.dist-info/WHEEL
featsql-0.1.1.dist-info/entry_points.txt
featsql-0.1.1.dist-info/top_level.txt
featsql-0.1.1.dist-info/RECORD
