Metadata-Version: 2.1
Name: featsql
Version: 0.1.1
Summary: Create features with sql
Home-page: https://github.com/ravennaro/featsql
Author: Ravenna Oliveria
Author-email: ravenna.rro@gmail.com
License: Apache Software License 2.0
Keywords: nbdev jupyter notebook python
Platform: UNKNOWN
Classifier: Development Status :: 4 - Beta
Classifier: Intended Audience :: Developers
Classifier: Natural Language :: English
Classifier: Programming Language :: Python :: 3.7
Classifier: Programming Language :: Python :: 3.8
Classifier: Programming Language :: Python :: 3.9
Classifier: Programming Language :: Python :: 3.10
Classifier: License :: OSI Approved :: Apache Software License
Requires-Python: >=3.7
License-File: LICENSE
Requires-Dist: fastcore
Requires-Dist: pandas
Provides-Extra: dev
Requires-Dist: ipykernel ; extra == 'dev'
Requires-Dist: nbdev ; extra == 'dev'
